objectlib/__init__.py
objectlib/detector.py
my_yolo_detector-0.1.0.dist-info/METADATA
my_yolo_detector-0.1.0.dist-info/WHEEL
my_yolo_detector-0.1.0.dist-info/top_level.txt
my_yolo_detector-0.1.0.dist-info/RECORD
