Metadata-Version: 2.2
Name: my_yolo_detector
Version: 0.1.0
Requires-Dist: ultralytics>=8.0.0
Requires-Dist: opencv-python>=4.5.0
Dynamic: requires-dist
